orjson-stubs/METADATA.toml
orjson-stubs/__init__.pyi
types_orjson-3.6.1.dist-info/METADATA
types_orjson-3.6.1.dist-info/WHEEL
types_orjson-3.6.1.dist-info/top_level.txt
types_orjson-3.6.1.dist-info/RECORD
