Metadata-Version: 2.1
Name: types-orjson
Version: 3.6.1
Summary: Typing stubs for orjson
Home-page: https://github.com/python/typeshed
License: Apache-2.0 license
Platform: UNKNOWN
Classifier: License :: OSI Approved :: Apache Software License
Classifier: Typing :: Typed
